libproc.py
libproc-0.2.dist-info/zip-safe
libproc-0.2.dist-info/metadata.json
libproc-0.2.dist-info/RECORD
libproc-0.2.dist-info/top_level.txt
libproc-0.2.dist-info/DESCRIPTION.rst
libproc-0.2.dist-info/WHEEL
libproc-0.2.dist-info/METADATA
